balladeer/__init__.py
balladeer/classic/__init__.py
balladeer/classic/cartography.py
balladeer/classic/drama.py
balladeer/classic/folio.py
balladeer/classic/gesture.py
balladeer/classic/speech.py
balladeer/classic/story.py
balladeer/classic/types.py
balladeer/classic/test/__init__.py
balladeer/classic/test/test_cartography.py
balladeer/classic/test/test_drama.py
balladeer/classic/test/test_folio.py
balladeer/classic/test/test_gesture.py
balladeer/classic/test/test_speech.py
balladeer/doc/changes.rst
balladeer/doc/drama.rst
balladeer/doc/entity.rst
balladeer/doc/index.rst
balladeer/doc/interaction.rst
balladeer/doc/intro.rst
balladeer/doc/map.rst
balladeer/doc/scene.rst
balladeer/doc/screenshots.rst
balladeer/doc/speech.rst
balladeer/doc/story.rst
balladeer/doc/style.rst
balladeer/doc/themes.rst
balladeer/doc/types.rst
balladeer/doc/web.rst
balladeer/doc/world.rst
balladeer/doc/_static/balladeer_doc_style.css
balladeer/doc/_static/bottles-shot.png
balladeer/doc/_static/cloak_of_darkness-screen.png
balladeer/doc/_static/styling_themes-shot.png
balladeer/doc/_templates/github.html
balladeer/doc/_templates/globaltoc.html
balladeer/doc/_templates/layout.html
balladeer/doc/_templates/localtoc.html
balladeer/doc/html/changes.html
balladeer/doc/html/drama.html
balladeer/doc/html/entity.html
balladeer/doc/html/genindex.html
balladeer/doc/html/index.html
balladeer/doc/html/interaction.html
balladeer/doc/html/intro.html
balladeer/doc/html/map.html
balladeer/doc/html/scene.html
balladeer/doc/html/screenshots.html
balladeer/doc/html/search.html
balladeer/doc/html/searchindex.js
balladeer/doc/html/speech.html
balladeer/doc/html/story.html
balladeer/doc/html/style.html
balladeer/doc/html/themes.html
balladeer/doc/html/types.html
balladeer/doc/html/web.html
balladeer/doc/html/world.html
balladeer/doc/html/_images/bottles-shot.png
balladeer/doc/html/_images/cloak_of_darkness-screen.png
balladeer/doc/html/_images/styling_themes-shot.png
balladeer/doc/html/_sources/changes.rst.txt
balladeer-0.59.0.dist-info/LICENSE
balladeer-0.59.0.dist-info/METADATA
balladeer-0.59.0.dist-info/WHEEL
balladeer-0.59.0.dist-info/top_level.txt
balladeer-0.59.0.dist-info/RECORD
