Metadata-Version: 2.2
Name: balladeer
Version: 0.59.0
Summary: Web-enabled interactive fiction framework.
Author-email: Tundish <tundish@gigeconomy.org.uk>
Maintainer-email: Tundish <tundish@gigeconomy.org.uk>
License:                     GNU GENERAL PUBLIC LICENSE
Keywords: speechmark,story,interactive fiction
Classifier: Development Status :: 4 - Beta
Classifier: Operating System :: OS Independent
Classifier: Programming Language :: Python :: 3.11
Requires-Python: >=3.11
License-File: LICENSE
Requires-Dist: busker>=0.22.0
Requires-Dist: hypercorn
Requires-Dist: python-multipart
Requires-Dist: speechmark>=0.10.0
Requires-Dist: starlette>=0.42.0
Requires-Dist: tomli>=2.0.0; python_version < "3.11"
Provides-Extra: classic
Requires-Dist: aiohttp; extra == "classic"
Requires-Dist: docutils==0.18.1; extra == "classic"
Requires-Dist: turberfield-catchphrase==0.25.0; extra == "classic"
Requires-Dist: turberfield-dialogue==0.47.0; extra == "classic"
Requires-Dist: turberfield-utils==0.47.0; extra == "classic"
Provides-Extra: docbuild
Requires-Dist: sphinx<=6.2.1; extra == "docbuild"
Requires-Dist: karma-sphinx-theme>=0.0.8; extra == "docbuild"
